mypuma/ANN_Lab.py
mypuma/CV_Lab.py
mypuma/ML_Lab.py
mypuma/__init__.py
mypuma/puma.py
mypuma-0.0.0.dist-info/LICENSE
mypuma-0.0.0.dist-info/METADATA
mypuma-0.0.0.dist-info/WHEEL
mypuma-0.0.0.dist-info/top_level.txt
mypuma-0.0.0.dist-info/RECORD
