Metadata-Version: 2.1
Name: mypuma
Version: 0.0.0
Summary: A helper library with useful functions.
Home-page: https://github.com/yourusername/myhelper
Author: puma
Author-email: puma.info@gmail.com
Classifier: Programming Language :: Python :: 3
Classifier: License :: OSI Approved :: MIT License
Classifier: Operating System :: OS Independent
Requires-Python: >=3.6
License-File: LICENSE
